synthyverse/__init__.py
synthyverse/benchmark/__init__.py
synthyverse/benchmark/imputation.py
synthyverse/benchmark/synthesis.py
synthyverse/benchmark/utils.py
synthyverse/evaluation/__init__.py
synthyverse/evaluation/eval.py
synthyverse/evaluation/fidelity.py
synthyverse/evaluation/privacy.py
synthyverse/evaluation/utility.py
synthyverse/evaluation/utils.py
synthyverse/generators/__init__.py
synthyverse/generators/base.py
synthyverse/generators/arf_generator/__init__.py
synthyverse/generators/arf_generator/arf.py
synthyverse/generators/bn_generator/__init__.py
synthyverse/generators/bn_generator/bn.py
synthyverse/generators/cdtd_generator/__init__.py
synthyverse/generators/cdtd_generator/cdtd.py
synthyverse/generators/cdtd_generator/cdtd_dir/__init__.py
synthyverse/generators/cdtd_generator/cdtd_dir/layers.py
synthyverse/generators/cdtd_generator/cdtd_dir/utils.py
synthyverse/generators/ctabgan_generator/__init__.py
synthyverse/generators/ctabgan_generator/ctab_gan.py
synthyverse/generators/ctgan_generator/__init__.py
synthyverse/generators/ctgan_generator/ct_gan.py
synthyverse/generators/forestdiffusion_generator/__init__.py
synthyverse/generators/forestdiffusion_generator/forestdiffusion.py
synthyverse/generators/nrgboost_generator/__init__.py
synthyverse/generators/nrgboost_generator/nrg_boost.py
synthyverse/generators/permutation_generator/__init__.py
synthyverse/generators/permutation_generator/permutation.py
synthyverse/generators/realtabformer_generator/__init__.py
synthyverse/generators/realtabformer_generator/real_tabformer.py
synthyverse/generators/synthpop_generator/__init__.py
synthyverse/generators/synthpop_generator/synth_pop.py
synthyverse/generators/tabargn_generator/__init__.py
synthyverse/generators/tabargn_generator/tabargn.py
synthyverse/generators/tabddpm_generator/__init__.py
synthyverse/generators/tabddpm_generator/tabddpm.py
synthyverse/generators/tabsyn_generator/__init__.py
synthyverse/generators/tabsyn_generator/tabsyn.py
synthyverse-0.1.3.dist-info/LICENSE
synthyverse-0.1.3.dist-info/METADATA
synthyverse-0.1.3.dist-info/WHEEL
synthyverse-0.1.3.dist-info/top_level.txt
synthyverse-0.1.3.dist-info/RECORD
