Metadata-Version: 2.1
Name: synthyverse
Version: 0.1.3
Summary: Synthetic data generation and evaluation library
Home-page: https://github.com/synthyverse/synthyverse
Author: Jim Achterberg, Saif Ul Islam, Zia Ur Rehman
Author-email: 
Classifier: Development Status :: 3 - Alpha
Classifier: Intended Audience :: Developers
Classifier: Intended Audience :: Science/Research
Classifier: License :: OSI Approved :: MIT License
Classifier: Programming Language :: Python :: 3
Classifier: Programming Language :: Python :: 3.8
Classifier: Programming Language :: Python :: 3.9
Classifier: Programming Language :: Python :: 3.10
Classifier: Programming Language :: Python :: 3.11
Classifier: Programming Language :: Python :: 3.12
Classifier: Topic :: Scientific/Engineering :: Artificial Intelligence
Classifier: Topic :: Software Development :: Libraries :: Python Modules
Requires-Python: >=3.8
License-File: LICENSE
Provides-Extra: arf
Requires-Dist: pandas; extra == "arf"
Requires-Dist: numpy; extra == "arf"
Requires-Dist: scikit-learn; extra == "arf"
Requires-Dist: arfpy; extra == "arf"
Provides-Extra: base
Requires-Dist: pandas; extra == "base"
Requires-Dist: numpy; extra == "base"
Requires-Dist: scikit-learn; extra == "base"
Provides-Extra: bn
Requires-Dist: pandas; extra == "bn"
Requires-Dist: numpy; extra == "bn"
Requires-Dist: scikit-learn; extra == "bn"
Requires-Dist: synthcity==0.2.12; extra == "bn"
Requires-Dist: opacus==1.5.3; extra == "bn"
Provides-Extra: cdtd
Requires-Dist: pandas; extra == "cdtd"
Requires-Dist: numpy; extra == "cdtd"
Requires-Dist: scikit-learn; extra == "cdtd"
Requires-Dist: torch; extra == "cdtd"
Requires-Dist: torch-ema; extra == "cdtd"
Requires-Dist: einops; extra == "cdtd"
Requires-Dist: tqdm; extra == "cdtd"
Provides-Extra: ctabgan
Requires-Dist: pandas; extra == "ctabgan"
Requires-Dist: numpy; extra == "ctabgan"
Requires-Dist: scikit-learn; extra == "ctabgan"
Requires-Dist: torch; extra == "ctabgan"
Requires-Dist: dython; extra == "ctabgan"
Requires-Dist: scipy; extra == "ctabgan"
Provides-Extra: ctgan
Requires-Dist: pandas; extra == "ctgan"
Requires-Dist: numpy; extra == "ctgan"
Requires-Dist: scikit-learn; extra == "ctgan"
Requires-Dist: ctgan==0.10.0; extra == "ctgan"
Provides-Extra: eval
Requires-Dist: torch; extra == "eval"
Requires-Dist: pandas; extra == "eval"
Requires-Dist: numpy; extra == "eval"
Requires-Dist: scikit-learn; extra == "eval"
Requires-Dist: xgboost; extra == "eval"
Requires-Dist: sdmetrics; extra == "eval"
Provides-Extra: forestdiffusion
Requires-Dist: pandas; extra == "forestdiffusion"
Requires-Dist: numpy; extra == "forestdiffusion"
Requires-Dist: scikit-learn; extra == "forestdiffusion"
Requires-Dist: ForestDiffusion; extra == "forestdiffusion"
Provides-Extra: full
Requires-Dist: dython; extra == "full"
Requires-Dist: einops; extra == "full"
Requires-Dist: pandas; extra == "full"
Requires-Dist: realtabformer; extra == "full"
Requires-Dist: tqdm; extra == "full"
Requires-Dist: opacus==1.5.3; extra == "full"
Requires-Dist: mostlyai-engine; extra == "full"
Requires-Dist: numpy; extra == "full"
Requires-Dist: sdmetrics; extra == "full"
Requires-Dist: scikit-learn; extra == "full"
Requires-Dist: icecream; extra == "full"
Requires-Dist: category-encoders; extra == "full"
Requires-Dist: tomli; extra == "full"
Requires-Dist: tomli-w; extra == "full"
Requires-Dist: xgboost; extra == "full"
Requires-Dist: scipy; extra == "full"
Requires-Dist: synthcity==0.2.12; extra == "full"
Requires-Dist: torch; extra == "full"
Requires-Dist: ctgan==0.10.0; extra == "full"
Requires-Dist: zero; extra == "full"
Requires-Dist: ForestDiffusion; extra == "full"
Requires-Dist: arfpy; extra == "full"
Requires-Dist: torch-ema; extra == "full"
Requires-Dist: utrees; extra == "full"
Provides-Extra: permutation
Requires-Dist: pandas; extra == "permutation"
Requires-Dist: numpy; extra == "permutation"
Requires-Dist: scikit-learn; extra == "permutation"
Provides-Extra: realtabformer
Requires-Dist: pandas; extra == "realtabformer"
Requires-Dist: numpy; extra == "realtabformer"
Requires-Dist: scikit-learn; extra == "realtabformer"
Requires-Dist: realtabformer; extra == "realtabformer"
Provides-Extra: tabargn
Requires-Dist: pandas; extra == "tabargn"
Requires-Dist: numpy; extra == "tabargn"
Requires-Dist: scikit-learn; extra == "tabargn"
Requires-Dist: mostlyai-engine; extra == "tabargn"
Provides-Extra: tabddpm
Requires-Dist: pandas; extra == "tabddpm"
Requires-Dist: numpy; extra == "tabddpm"
Requires-Dist: scikit-learn; extra == "tabddpm"
Requires-Dist: synthcity==0.2.12; extra == "tabddpm"
Requires-Dist: opacus==1.5.3; extra == "tabddpm"
Provides-Extra: tabsyn
Requires-Dist: pandas; extra == "tabsyn"
Requires-Dist: numpy; extra == "tabsyn"
Requires-Dist: scikit-learn; extra == "tabsyn"
Requires-Dist: torch; extra == "tabsyn"
Requires-Dist: tqdm; extra == "tabsyn"
Requires-Dist: scipy; extra == "tabsyn"
Requires-Dist: category-encoders; extra == "tabsyn"
Requires-Dist: zero; extra == "tabsyn"
Requires-Dist: icecream; extra == "tabsyn"
Requires-Dist: tomli-w; extra == "tabsyn"
Requires-Dist: tomli; extra == "tabsyn"
Provides-Extra: tvae
Requires-Dist: pandas; extra == "tvae"
Requires-Dist: numpy; extra == "tvae"
Requires-Dist: scikit-learn; extra == "tvae"
Requires-Dist: ctgan==0.10.0; extra == "tvae"
Provides-Extra: unmaskingtrees
Requires-Dist: pandas; extra == "unmaskingtrees"
Requires-Dist: numpy; extra == "unmaskingtrees"
Requires-Dist: scikit-learn; extra == "unmaskingtrees"
Requires-Dist: utrees; extra == "unmaskingtrees"
